lbmd_sota/__init__.py
lbmd_sota/cli.py
lbmd_sota/comparative_analysis/__init__.py
lbmd_sota/comparative_analysis/baseline_comparator.py
lbmd_sota/comparative_analysis/example_usage.py
lbmd_sota/comparative_analysis/failure_mode_analyzer.py
lbmd_sota/comparative_analysis/insight_differentiator.py
lbmd_sota/comparative_analysis/test_comparative_analysis.py
lbmd_sota/core/__init__.py
lbmd_sota/core/analyzer.py
lbmd_sota/core/config.py
lbmd_sota/core/data_models.py
lbmd_sota/core/interfaces.py
lbmd_sota/empirical_validation/__init__.py
lbmd_sota/empirical_validation/ablation_study_runner.py
lbmd_sota/empirical_validation/architecture_manager.py
lbmd_sota/empirical_validation/boundary_detectors.py
lbmd_sota/empirical_validation/clustering_algorithms.py
lbmd_sota/empirical_validation/dataset_loaders.py
lbmd_sota/empirical_validation/manifold_learners.py
lbmd_sota/empirical_validation/multi_dataset_evaluator.py
lbmd_sota/empirical_validation/statistical_analyzer.py
lbmd_sota/empirical_validation/test_ablation_study.py
lbmd_sota/empirical_validation/test_component_ablation.py
lbmd_sota/empirical_validation/test_component_ablation_integration.py
lbmd_sota/empirical_validation/test_component_workflows.py
lbmd_sota/empirical_validation/test_parameter_sweep.py
lbmd_sota/evaluation/__init__.py
lbmd_sota/evaluation/ablation_studies.py
lbmd_sota/evaluation/experiment_orchestrator.py
lbmd_sota/evaluation/human_evaluation.py
lbmd_sota/evaluation/performance_tester.py
lbmd_sota/evaluation/report_generator.py
lbmd_sota/evaluation/statistical_analysis.py
lbmd_sota/evaluation/success_metrics.py
lbmd_sota/evaluation/test_evaluation_system.py
lbmd_sota/examples/__init__.py
lbmd_sota/examples/basic_usage.py
lbmd_sota/examples/transformer_analysis.py
lbmd_sota/model_improvement/__init__.py
lbmd_sota/model_improvement/architecture_enhancer.py
lbmd_sota/model_improvement/augmentation_strategy.py
lbmd_sota/model_improvement/boundary_loss_designer.py
lbmd_sota-1.0.1.dist-info/licenses/LICENSE
lbmd_sota-1.0.1.dist-info/METADATA
lbmd_sota-1.0.1.dist-info/WHEEL
lbmd_sota-1.0.1.dist-info/entry_points.txt
lbmd_sota-1.0.1.dist-info/top_level.txt
lbmd_sota-1.0.1.dist-info/RECORD
