Metadata-Version: 2.4
Name: lbmd-sota
Version: 1.0.1
Summary: Latent Boundary Manifold Decomposition for State-of-the-Art Mechanistic Interpretability
Home-page: https://github.com/SV-18/lbmd-sota
Author: Srikanth Vemula
Author-email: Srikanth Vemula <srikanthv0567@gmail.com>
License: MIT
Project-URL: Homepage, https://github.com/SV-18/lbmd-sota
Project-URL: Documentation, https://github.com/SV-18/lbmd-sota#readme
Project-URL: Repository, https://github.com/SV-18/lbmd-sota.git
Project-URL: Bug Tracker, https://github.com/SV-18/lbmd-sota/issues
Keywords: machine learning,interpretability,neural networks,computer vision
Classifier: Development Status :: 3 - Alpha
Classifier: Intended Audience :: Developers
Classifier: Intended Audience :: Science/Research
Classifier: License :: OSI Approved :: MIT License
Classifier: Operating System :: OS Independent
Classifier: Programming Language :: Python :: 3
Classifier: Programming Language :: Python :: 3.8
Classifier: Programming Language :: Python :: 3.9
Classifier: Programming Language :: Python :: 3.10
Classifier: Programming Language :: Python :: 3.11
Classifier: Topic :: Scientific/Engineering :: Artificial Intelligence
Requires-Python: >=3.8
License-File: LICENSE
Requires-Dist: torch>=1.8.0
Requires-Dist: torchvision>=0.9.0
Requires-Dist: numpy>=1.19.0
Requires-Dist: scipy>=1.6.0
Requires-Dist: scikit-learn>=0.24.0
Requires-Dist: matplotlib>=3.3.0
Requires-Dist: seaborn>=0.11.0
Requires-Dist: plotly>=5.0.0
Requires-Dist: pandas>=1.2.0
Requires-Dist: tqdm>=4.60.0
Requires-Dist: pyyaml>=5.4.0
Requires-Dist: pillow>=8.0.0
Requires-Dist: opencv-python>=4.5.0
Provides-Extra: dev
Requires-Dist: pytest>=6.0.0; extra == "dev"
Requires-Dist: pytest-cov>=2.10.0; extra == "dev"
Requires-Dist: black>=21.0.0; extra == "dev"
Requires-Dist: flake8>=3.8.0; extra == "dev"
Requires-Dist: mypy>=0.800; extra == "dev"
Provides-Extra: interactive
Requires-Dist: ipywidgets>=7.6.0; extra == "interactive"
Requires-Dist: jupyter>=1.0.0; extra == "interactive"
Requires-Dist: notebook>=6.0.0; extra == "interactive"
Provides-Extra: full
Requires-Dist: umap-learn>=0.5.0; extra == "full"
Requires-Dist: networkx>=2.5.0; extra == "full"
Requires-Dist: dash>=2.0.0; extra == "full"
Requires-Dist: dash-bootstrap-components>=1.0.0; extra == "full"
Dynamic: author
Dynamic: home-page
Dynamic: license-file
Dynamic: requires-python
